LICENSE
snakypy/zshpower/__init__.py
snakypy/zshpower/__main__.py
snakypy/zshpower/cli.py
snakypy/zshpower/commands/__init__.py
snakypy/zshpower/commands/activate.py
snakypy/zshpower/commands/config.py
snakypy/zshpower/commands/credits.py
snakypy/zshpower/commands/cron.py
snakypy/zshpower/commands/deactivate.py
snakypy/zshpower/commands/init.py
snakypy/zshpower/commands/logs.py
snakypy/zshpower/commands/reset.py
snakypy/zshpower/commands/sync.py
snakypy/zshpower/commands/themes.py
snakypy/zshpower/commands/uninstall.py
snakypy/zshpower/commands/utils/__init__.py
snakypy/zshpower/commands/utils/handle.py
snakypy/zshpower/config/__init__.py
snakypy/zshpower/config/base.py
snakypy/zshpower/config/bootstrap.py
snakypy/zshpower/config/config.py
snakypy/zshpower/config/cron.py
snakypy/zshpower/config/menu.py
snakypy/zshpower/config/zshrc.py
snakypy/zshpower/database/__init__.py
snakypy/zshpower/database/dao.py
snakypy/zshpower/database/sql.py
snakypy/zshpower/draw.py
snakypy/zshpower/prompt/__init__.py
snakypy/zshpower/prompt/sections/__init__.py
snakypy/zshpower/prompt/sections/c.py
snakypy/zshpower/prompt/sections/cmake.py
snakypy/zshpower/prompt/sections/command.py
snakypy/zshpower/prompt/sections/cpp.py
snakypy/zshpower/prompt/sections/crystal.py
snakypy/zshpower/prompt/sections/dart.py
snakypy/zshpower/prompt/sections/deno.py
snakypy/zshpower/prompt/sections/directory.py
snakypy/zshpower/prompt/sections/docker.py
snakypy/zshpower/prompt/sections/dotnet.py
snakypy/zshpower/prompt/sections/elixir.py
snakypy/zshpower/prompt/sections/ember.py
snakypy/zshpower/prompt/sections/erlang.py
snakypy/zshpower/prompt/sections/git.py
snakypy/zshpower/prompt/sections/golang.py
snakypy/zshpower/prompt/sections/gulp.py
snakypy/zshpower/prompt/sections/helm.py
snakypy/zshpower/prompt/sections/hostname.py
snakypy/zshpower/prompt/sections/java.py
snakypy/zshpower/prompt/sections/julia.py
snakypy/zshpower/prompt/sections/jump_line.py
snakypy/zshpower/prompt/sections/kotlin.py
zshpower-0.12.0.dist-info/entry_points.txt
zshpower-0.12.0.dist-info/LICENSE
zshpower-0.12.0.dist-info/WHEEL
zshpower-0.12.0.dist-info/METADATA
zshpower-0.12.0.dist-info/RECORD
