Metadata-Version: 2.1
Name: zshpower
Version: 0.12.0
Summary: ZSHPower is a theme for ZSH with a manager.
Home-page: https://github.com/snakypy/zshpower
License: MIT
Keywords: zsh-theme,snakypy,zsh,theme,power
Author: William C. Canin
Author-email: william.costa.canin@gmail.com
Requires-Python: >=3.9,<4.0
Classifier: Intended Audience :: Developers
Classifier: License :: OSI Approved :: MIT License
Classifier: Operating System :: MacOS
Classifier: Operating System :: POSIX :: Linux
Classifier: Operating System :: Unix
Classifier: Programming Language :: Python :: 3
Classifier: Programming Language :: Python :: 3.10
Classifier: Programming Language :: Python :: 3.9
Requires-Dist: docopt (>=0.6.2,<0.7.0)
Requires-Dist: snakypy-helpers (>=0.3.1,<0.4.0)
Requires-Dist: tomlkit (>=0.11.1,<0.12.0)
Project-URL: Bug Tracker, https://github.com/snakypy/zshpower/issues
Project-URL: Repository, https://github.com/snakypy/zshpower
